guardata/__init__.py
guardata/_version.py
guardata/cli.py
guardata/cli_utils.py
guardata/event_bus.py
guardata/logging.py
guardata/monitoring.py
guardata/service_nursery.py
guardata/types.py
guardata/utils.py
guardata/win32.py
guardata/api/__init__.py
guardata/api/transport.py
guardata/api/version.py
guardata/api/data/__init__.py
guardata/api/data/base.py
guardata/api/data/certif.py
guardata/api/data/entry.py
guardata/api/data/invite.py
guardata/api/data/invite_claim.py
guardata/api/data/manifest.py
guardata/api/data/message.py
guardata/api/protocol/__init__.py
guardata/api/protocol/base.py
guardata/api/protocol/block.py
guardata/api/protocol/cmds.py
guardata/api/protocol/events.py
guardata/api/protocol/handshake.py
guardata/api/protocol/invite.py
guardata/api/protocol/message.py
guardata/api/protocol/organization.py
guardata/api/protocol/ping.py
guardata/api/protocol/realm.py
guardata/api/protocol/types.py
guardata/api/protocol/user.py
guardata/api/protocol/vlob.py
guardata/client/__init__.py
guardata/client/client_events.py
guardata/client/config.py
guardata/client/ipcinterface.py
guardata/client/local_device.py
guardata/client/logged_client.py
guardata/client/messages_monitor.py
guardata/client/remote_devices_manager.py
guardata/client/sync_monitor.py
guardata/client/trustchain.py
guardata/client/win_registry.py
guardata/client/backend_connection/__init__.py
guardata/client/backend_connection/apiv1_administration.py
guardata/client/backend_connection/apiv1_annonymous.py
guardata/client/backend_connection/authenticated.py
guardata/client/backend_connection/cmds.py
guardata/client/backend_connection/exceptions.py
guardata/client/backend_connection/expose_cmds.py
guardata/client/backend_connection/invited.py
guardata/client/backend_connection/transport.py
guardata/client/cli/__init__.py
guardata/client/cli/__main__.py
guardata/client/cli/bootstrap_organization.py
guardata/client/cli/create_organization.py
guardata/client/cli/create_workspace.py
guardata-0.2.4.dist-info/AUTHORS.md
guardata-0.2.4.dist-info/LICENSE
guardata-0.2.4.dist-info/METADATA
guardata-0.2.4.dist-info/WHEEL
guardata-0.2.4.dist-info/entry_points.txt
guardata-0.2.4.dist-info/top_level.txt
guardata-0.2.4.dist-info/RECORD
