Metadata-Version: 2.1
Name: guardata
Version: 0.2.4
Summary: Desktop client for a modern and trustless data cloud storage service
Home-page: https://guardata.app
Author: BitLogiK
Author-email: contact@bitlogik.fr
License: AGPLv3
Keywords: cloud data storage sharing cryptography
Platform: UNKNOWN
Classifier: Development Status :: 5 - Production/Stable
Classifier: Programming Language :: Python :: 3
Classifier: License :: OSI Approved :: GNU Affero General Public License v3
Classifier: Operating System :: Microsoft :: Windows :: Windows 8
Classifier: Operating System :: Microsoft :: Windows :: Windows 8.1
Classifier: Operating System :: Microsoft :: Windows :: Windows 10
Classifier: Operating System :: POSIX :: Linux
Classifier: Operating System :: MacOS
Classifier: Topic :: Communications :: File Sharing
Classifier: Topic :: Office/Business
Classifier: Topic :: Security :: Cryptography
Classifier: Topic :: System :: Archiving :: Backup
Requires-Python: >=3.6
License-File: LICENSE
License-File: AUTHORS.md
Requires-Dist: attrs (==19.2.0)
Requires-Dist: click (==7.0)
Requires-Dist: msgpack (==0.6.2)
Requires-Dist: wsproto (==1.0.0)
Requires-Dist: toastedmarshmallow (==0.2.6)
Requires-Dist: pendulum (==2.1.2)
Requires-Dist: PyNaCl (==1.4.0)
Requires-Dist: trio (==0.16.0)
Requires-Dist: async-generator (>=1.9)
Requires-Dist: structlog (==19.2.0)
Requires-Dist: importlib-resources (==1.0.2)
Requires-Dist: colorama (==0.4.0)
Requires-Dist: async-exit-stack (==1.0.1)
Requires-Dist: outcome (==1.0.0)
Requires-Dist: packaging (==20.4)
Requires-Dist: PyQt5 (==5.14.2)
Requires-Dist: pyqt5-sip (==12.8.0)
Requires-Dist: Babel (==2.6.0)
Requires-Dist: zxcvbn (==4.4.28)
Requires-Dist: psutil (==5.6.3)
Requires-Dist: fusepy (==3.0.1) ; platform_system == "Linux" or platform_system == "Darwin"
Requires-Dist: winfspy (==0.8.0) ; platform_system == "Windows"
Requires-Dist: contextvars (==2.1) ; python_version < "3.7"
Provides-Extra: all
Requires-Dist: jinja2 (==2.11.2) ; extra == 'all'
Requires-Dist: pytest (==5.4.3) ; extra == 'all'
Requires-Dist: pytest-xdist (==1.32.0) ; extra == 'all'
Requires-Dist: pytest-trio (==0.5.2) ; extra == 'all'
Requires-Dist: pytest-qt (==3.3.0) ; extra == 'all'
Requires-Dist: pytest-rerunfailures (==9.0) ; extra == 'all'
Requires-Dist: hypothesis (==5.3.0) ; extra == 'all'
Requires-Dist: hypothesis-trio (==0.5.0) ; extra == 'all'
Requires-Dist: trustme (==0.6.0) ; extra == 'all'
Requires-Dist: pbr (==4.0.2) ; extra == 'all'
Requires-Dist: triopg (==0.5.0) ; extra == 'all'
Requires-Dist: trio-asyncio (==0.11.0) ; extra == 'all'
Requires-Dist: pywin32 (==227) ; (platform_system == "Windows") and extra == 'all'
Provides-Extra: dev
Requires-Dist: jinja2 (==2.11.2) ; extra == 'dev'
Requires-Dist: pytest (==5.4.3) ; extra == 'dev'
Requires-Dist: pytest-xdist (==1.32.0) ; extra == 'dev'
Requires-Dist: pytest-trio (==0.5.2) ; extra == 'dev'
Requires-Dist: pytest-qt (==3.3.0) ; extra == 'dev'
Requires-Dist: pytest-rerunfailures (==9.0) ; extra == 'dev'
Requires-Dist: hypothesis (==5.3.0) ; extra == 'dev'
Requires-Dist: hypothesis-trio (==0.5.0) ; extra == 'dev'
Requires-Dist: trustme (==0.6.0) ; extra == 'dev'
Requires-Dist: pbr (==4.0.2) ; extra == 'dev'
Requires-Dist: triopg (==0.5.0) ; extra == 'dev'
Requires-Dist: trio-asyncio (==0.11.0) ; extra == 'dev'
Requires-Dist: pywin32 (==227) ; (platform_system == "Windows") and extra == 'dev'
